endaq/ide/__init__.py
endaq/ide/files.py
endaq/ide/gdrive.py
endaq/ide/info.py
endaq/ide/measurement.py
endaq/ide/util.py
endaq_ide-1.1.0.dist-info/LICENSE
endaq_ide-1.1.0.dist-info/METADATA
endaq_ide-1.1.0.dist-info/WHEEL
endaq_ide-1.1.0.dist-info/top_level.txt
endaq_ide-1.1.0.dist-info/RECORD
