Metadata-Version: 2.1
Name: endaq-ide
Version: 1.1.0
Summary: A comprehensive, user-centric Python API for working with enDAQ data and devices
Home-page: https://github.com/MideTechnology/endaq-python-ide
Author: Mide Technology
Author-email: help@mide.com
License: MIT
Keywords: ebml binary ide mide endaq
Platform: UNKNOWN
Classifier: Development Status :: 4 - Beta
Classifier: License :: OSI Approved :: MIT License
Classifier: Natural Language :: English
Classifier: Programming Language :: Python :: 3.7
Classifier: Programming Language :: Python :: 3.8
Classifier: Programming Language :: Python :: 3.9
Classifier: Topic :: Scientific/Engineering
License-File: LICENSE
Requires-Dist: numpy (>=1.16.6)
Requires-Dist: ebmlite (>=3.0.0)
Requires-Dist: idelib (>=3.2.3)
Requires-Dist: requests
Requires-Dist: pandas (>=1.3)
Requires-Dist: jinja2
Provides-Extra: example
Requires-Dist: numpy (>=1.16.6) ; extra == 'example'
Requires-Dist: ebmlite (>=3.0.0) ; extra == 'example'
Requires-Dist: idelib (>=3.2.3) ; extra == 'example'
Requires-Dist: requests ; extra == 'example'
Requires-Dist: pandas (>=1.3) ; extra == 'example'
Requires-Dist: jinja2 ; extra == 'example'
Provides-Extra: test
Requires-Dist: numpy (>=1.16.6) ; extra == 'test'
Requires-Dist: ebmlite (>=3.0.0) ; extra == 'test'
Requires-Dist: idelib (>=3.2.3) ; extra == 'test'
Requires-Dist: requests ; extra == 'test'
Requires-Dist: pandas (>=1.3) ; extra == 'test'
Requires-Dist: jinja2 ; extra == 'test'
Requires-Dist: pytest ; extra == 'test'
Requires-Dist: pytest-cov ; extra == 'test'
